backports/__init__.py
backports/textwrap.py
backports.textwrap-0.1.5.dist-info/WHEEL
backports.textwrap-0.1.5.dist-info/METADATA
backports.textwrap-0.1.5.dist-info/RECORD
