Metadata-Version: 2.1
Name: backports.textwrap
Version: 0.1.5
Summary: A backport of upcoming python/cpython#28136
Author: Tip ten Brink
Author-email: 75669206+tiptenbrink@users.noreply.github.com
Requires-Python: >=3.5,<4.0
Classifier: Programming Language :: Python :: 3
Classifier: Programming Language :: Python :: 3.10
Classifier: Programming Language :: Python :: 3.5
Classifier: Programming Language :: Python :: 3.6
Classifier: Programming Language :: Python :: 3.7
Classifier: Programming Language :: Python :: 3.8
Classifier: Programming Language :: Python :: 3.9
Project-URL: Source Code, https://github.com/tiptenbrink/textwrap
